ftmscan_sdk/__init__.py
ftmscan_sdk/client/__init__.py
ftmscan_sdk/modules/__init__.py
ftmscan_sdk/modules/account/__init__.py
ftmscan_sdk/modules/account/account_module.py
ftmscan_sdk/modules/account/account_typing.py
ftmscan_sdk/utils/__init__.py
ftmscan_sdk/utils/custom_logger.py
ftmscan_sdk-0.5.4.dist-info/METADATA
ftmscan_sdk-0.5.4.dist-info/WHEEL
ftmscan_sdk-0.5.4.dist-info/licenses/LICENSE
ftmscan_sdk-0.5.4.dist-info/RECORD
