Metadata-Version: 2.3
Name: ftmscan-sdk
Version: 0.5.4
Summary: A sdk for interacting with ftmscan.com
Project-URL: Homepage, https://github.com/BoysOfCannabis/ftmscan-sdk
Project-URL: Issues, https://github.com/BoysOfCannabis/ftmscan-sdk/issues
Project-URL: Repository, https://github.com/BoysOfCannabis/ftmscan-sdk.git
Author-email: Omid Shahsavarzadeh <omidsha@pm.me>, Kianoush Mahboob <kianoushmhaboob@gmail.com>
License-File: LICENSE
Classifier: License :: OSI Approved :: MIT License
Classifier: Operating System :: OS Independent
Classifier: Programming Language :: Python :: 3
Requires-Python: >=3.11
